{"title":"The Inbetweeners Movie (2011) .{Good_Torrent}","uid":6906788,"size":659317756,"categoryP":"video","categoryS":"movies","magnet":"?xt=urn:btih:11b282509813dfc377224f166552aa53367142cb&amp;dn=The+Inbetweeners+Movie+%282011%29+.%7BGood_Torrent%7D&amp;tr=udp%3A%2F%2Ftracker.openbittorrent.com%3A80&amp;tr=udp%3A%2F%2Fopen.demonii.com%3A1337&amp;tr=udp%3A%2F%2Ftracker.coppersurfer.tk%3A6969&amp;tr=udp%3A%2F%2Fexodus.desync.com%3A6969","seeders":0,"leechers":0,"uploader":null,"files":3,"time":1324630786,"description":"720p","torrent":{"xt":"urn:btih:11b282509813dfc377224f166552aa53367142cb","amp;dn":"The+Inbetweeners+Movie+%282011%29+.%7BGood_Torrent%7D","amp;tr":["udp%3A%2F%2Ftracker.openbittorrent.com%3A80","udp%3A%2F%2Fopen.demonii.com%3A1337","udp%3A%2F%2Ftracker.coppersurfer.tk%3A6969","udp%3A%2F%2Fexodus.desync.com%3A6969"],"infoHash":"11b282509813dfc377224f166552aa53367142cb","infoHashBuffer":{"type":"Buffer","data":[17,178,130,80,152,19,223,195,119,34,79,22,101,82,170,83,54,113,66,203]},"announce":[],"urlList":[]}}