{"title":"BlackGFs 16 10 12 Harmony Rose Galactic Ass XXX 1080p","uid":16012572,"size":2473517717,"categoryP":"porn","categoryS":"movie_clips","magnet":"?xt=urn:btih:1426b126d8191f76ace4392347d994931138c85b&amp;dn=BlackGFs+16+10+12+Harmony+Rose+Galactic+Ass+XXX+1080p&amp;tr=udp%3A%2F%2Ftracker.leechers-paradise.org%3A6969&amp;tr=udp%3A%2F%2Fzer0day.ch%3A1337&amp;tr=udp%3A%2F%2Fopen.demonii.com%3A1337&amp;tr=udp%3A%2F%2Ftracker.coppersurfer.tk%3A6969&amp;tr=udp%3A%2F%2Fexodus.desync.com%3A6969","seeders":0,"leechers":1,"uploader":"JohnDevicariis","files":3,"time":1476252655,"description":"\n\n  Image Links \t:  http://imgshag.com/image/TELOx \n\n Image Links \t:  http://imgshag.com/image/TEUPo  \n\n  Image Links \t:  http://imgshag.com/image/TEeWI  \n\n  Image Sheet \t:  http://imgshag.com/image/TElNt \n\n \t \t \t Get More Small Sized XXX Videos \n \n \t   https://thepiratebay.se/user/johndevicariis/506","torrent":{"xt":"urn:btih:1426b126d8191f76ace4392347d994931138c85b","amp;dn":"BlackGFs+16+10+12+Harmony+Rose+Galactic+Ass+XXX+1080p","amp;tr":["udp%3A%2F%2Ftracker.leechers-paradise.org%3A6969","udp%3A%2F%2Fzer0day.ch%3A1337","udp%3A%2F%2Fopen.demonii.com%3A1337","udp%3A%2F%2Ftracker.coppersurfer.tk%3A6969","udp%3A%2F%2Fexodus.desync.com%3A6969"],"infoHash":"1426b126d8191f76ace4392347d994931138c85b","infoHashBuffer":{"type":"Buffer","data":[20,38,177,38,216,25,31,118,172,228,57,35,71,217,148,147,17,56,200,91]},"announce":[],"urlList":[]}}