{"title":"PornMegaLoad 16 09 14 Carly Parker Hot Hooter Ho XXX MP4","uid":15836543,"size":175975770,"categoryP":"porn","categoryS":"movie_clips","magnet":"?xt=urn:btih:1689660783c74de9cd693bbafe1c14ddc3b20bbb&amp;dn=PornMegaLoad+16+09+14+Carly+Parker+Hot+Hooter+Ho+XXX+MP4+&amp;tr=udp%3A%2F%2Ftracker.leechers-paradise.org%3A6969&amp;tr=udp%3A%2F%2Fzer0day.ch%3A1337&amp;tr=udp%3A%2F%2Fopen.demonii.com%3A1337&amp;tr=udp%3A%2F%2Ftracker.coppersurfer.tk%3A6969&amp;tr=udp%3A%2F%2Fexodus.desync.com%3A6969","seeders":0,"leechers":5,"uploader":"thfatboys","files":1,"time":1473978168,"description":"Screens: \nhttp://imgpeak.com/img-57dae41239c94.html","torrent":{"xt":"urn:btih:1689660783c74de9cd693bbafe1c14ddc3b20bbb","amp;dn":"PornMegaLoad+16+09+14+Carly+Parker+Hot+Hooter+Ho+XXX+MP4+","amp;tr":["udp%3A%2F%2Ftracker.leechers-paradise.org%3A6969","udp%3A%2F%2Fzer0day.ch%3A1337","udp%3A%2F%2Fopen.demonii.com%3A1337","udp%3A%2F%2Ftracker.coppersurfer.tk%3A6969","udp%3A%2F%2Fexodus.desync.com%3A6969"],"infoHash":"1689660783c74de9cd693bbafe1c14ddc3b20bbb","infoHashBuffer":{"type":"Buffer","data":[22,137,102,7,131,199,77,233,205,105,59,186,254,28,20,221,195,178,11,187]},"announce":[],"urlList":[]}}