{"title":"Free Encoder 5.7 [VERIFIED] By Team Nanban","uid":6884521,"size":6373238,"categoryP":"applications","categoryS":"windows","magnet":"?xt=urn:btih:2cdf6437f0f34a9cacc6ce139d120138e1c2da64&amp;dn=Free+Encoder+5.7+%5BVERIFIED%5D+By+Team+Nanban&amp;tr=udp%3A%2F%2Ftracker.openbittorrent.com%3A80&amp;tr=udp%3A%2F%2Fopen.demonii.com%3A1337&amp;tr=udp%3A%2F%2Ftracker.coppersurfer.tk%3A6969&amp;tr=udp%3A%2F%2Fexodus.desync.com%3A6969","seeders":0,"leechers":0,"uploader":"594mgnav","files":2,"time":1323776250,"description":"Free Encoder 5.7 [VERIFIED] By Team Nanban[TPB]\n\nFreecorder makes it easy to save video and audio from the web, \nand convert to many popular formats. Once Freecorder is installed, \njust use the following buttons in your browser.\n \nFEATURES:\n\n\n1. YouTube Downloader Tool: Save the video you are watching from YouTube and other    \nsites.\n\n2. Video History Tool: Save recently viewed videos on your PC's hard drive. \n\n3. Record Audio/MP3 Tool: Record any sound you can hear from your PC's speakers.\n\n4. Convert Tool: An easy to use file format converter for video and audio.\n\n5. Watch TV from channels all over the world.\n\n6. Enjoy Radio from hundreds of stations. (You can even record radio using Freecorder!)\n\n7. Freecorder 4 also makes common searches easier. Highlight any text in your browser,and it appears in the search box for a quick Google search. \nYou can also do video searches, site searches, and other cool things.\n\nPlz seed after downloading....","torrent":{"xt":"urn:btih:2cdf6437f0f34a9cacc6ce139d120138e1c2da64","amp;dn":"Free+Encoder+5.7+%5BVERIFIED%5D+By+Team+Nanban","amp;tr":["udp%3A%2F%2Ftracker.openbittorrent.com%3A80","udp%3A%2F%2Fopen.demonii.com%3A1337","udp%3A%2F%2Ftracker.coppersurfer.tk%3A6969","udp%3A%2F%2Fexodus.desync.com%3A6969"],"infoHash":"2cdf6437f0f34a9cacc6ce139d120138e1c2da64","infoHashBuffer":{"type":"Buffer","data":[44,223,100,55,240,243,74,156,172,198,206,19,157,18,1,56,225,194,218,100]},"announce":[],"urlList":[]}}