{"title":"Total Uninstall Ultimate 6.14.0 Pre-Activated","uid":16035824,"size":13717881,"categoryP":"applications","categoryS":"windows","magnet":"?xt=urn:btih:318afa61cbd6dcef4c3b605320e1ff2ef4a10472&amp;dn=Total+Uninstall+Ultimate+6.14.0+Pre-Activated&amp;tr=udp%3A%2F%2Ftracker.leechers-paradise.org%3A6969&amp;tr=udp%3A%2F%2Fzer0day.ch%3A1337&amp;tr=udp%3A%2F%2Fopen.demonii.com%3A1337&amp;tr=udp%3A%2F%2Ftracker.coppersurfer.tk%3A6969&amp;tr=udp%3A%2F%2Fexodus.desync.com%3A6969","seeders":0,"leechers":0,"uploader":"yBorhand","files":1,"time":1476481477,"description":"\n\r\n\r\n\r\n1) Unpack and install\r\n2) Use the key generator to generate a valid serial\r\n3) Enjoy this release!\r\n\r\nDon't Forget to buy the program","torrent":{"xt":"urn:btih:318afa61cbd6dcef4c3b605320e1ff2ef4a10472","amp;dn":"Total+Uninstall+Ultimate+6.14.0+Pre-Activated","amp;tr":["udp%3A%2F%2Ftracker.leechers-paradise.org%3A6969","udp%3A%2F%2Fzer0day.ch%3A1337","udp%3A%2F%2Fopen.demonii.com%3A1337","udp%3A%2F%2Ftracker.coppersurfer.tk%3A6969","udp%3A%2F%2Fexodus.desync.com%3A6969"],"infoHash":"318afa61cbd6dcef4c3b605320e1ff2ef4a10472","infoHashBuffer":{"type":"Buffer","data":[49,138,250,97,203,214,220,239,76,59,96,83,32,225,255,46,244,161,4,114]},"announce":[],"urlList":[]}}