{"title":"Mila Fyre mp4","uid":15914199,"size":303177643,"categoryP":"porn","categoryS":"movie_clips","magnet":"?xt=urn:btih:35353a39443dda173c14437c50906cd5d3dc37cf&amp;dn=Mila+Fyre+mp4&amp;tr=udp%3A%2F%2Ftracker.leechers-paradise.org%3A6969&amp;tr=udp%3A%2F%2Fzer0day.ch%3A1337&amp;tr=udp%3A%2F%2Fopen.demonii.com%3A1337&amp;tr=udp%3A%2F%2Ftracker.coppersurfer.tk%3A6969&amp;tr=udp%3A%2F%2Fexodus.desync.com%3A6969","seeders":0,"leechers":1,"uploader":"XXX-Pack","files":1,"time":1475178970,"description":"\n\n  Image Links \t:  http://imgbonk.com/image/LHIfQ  \n\n  Image Links \t:  http://imgbonk.com/image/LHj5K  \n\n  Image Sheet \t:  http://imgshag.com/image/XbTNy \n\n \t \t \t Get More Small Sized XXX Videos \n \n \t   https://thepiratebay.se/user/xxx-pack/506","torrent":{"xt":"urn:btih:35353a39443dda173c14437c50906cd5d3dc37cf","amp;dn":"Mila+Fyre+mp4","amp;tr":["udp%3A%2F%2Ftracker.leechers-paradise.org%3A6969","udp%3A%2F%2Fzer0day.ch%3A1337","udp%3A%2F%2Fopen.demonii.com%3A1337","udp%3A%2F%2Ftracker.coppersurfer.tk%3A6969","udp%3A%2F%2Fexodus.desync.com%3A6969"],"infoHash":"35353a39443dda173c14437c50906cd5d3dc37cf","infoHashBuffer":{"type":"Buffer","data":[53,53,58,57,68,61,218,23,60,20,67,124,80,144,108,213,211,220,55,207]},"announce":[],"urlList":[]}}