{"title":"Garmin City Navigator Europe 2016-10-11 free osm","uid":16009404,"size":1503793375,"categoryP":"applications","categoryS":"handheld","magnet":"?xt=urn:btih:37a04f3357d9662cb02e80410ea31424525e1550&amp;dn=Garmin+City+Navigator+Europe+2016-10-11+free+osm&amp;tr=udp%3A%2F%2Ftracker.leechers-paradise.org%3A6969&amp;tr=udp%3A%2F%2Fzer0day.ch%3A1337&amp;tr=udp%3A%2F%2Fopen.demonii.com%3A1337&amp;tr=udp%3A%2F%2Ftracker.coppersurfer.tk%3A6969&amp;tr=udp%3A%2F%2Fexodus.desync.com%3A6969","seeders":0,"leechers":0,"uploader":"Win32netsky","files":1,"time":1476214525,"description":"Hello\r\n\r\nThis is:\r\nGarmin City Navigator Europe 2016-10-11 free osm\r\n\r\nCountry List:\r\nGermany, Denmark, Austria, Suisse\r\n\r\nMore Information: \nhttp://wiki.openstreetmap.org/wiki/OSM_Transport_Karte\r\n\r\nThis torrent has permanent 24h upload support.\r\n\r\nBest Regards","torrent":{"xt":"urn:btih:37a04f3357d9662cb02e80410ea31424525e1550","amp;dn":"Garmin+City+Navigator+Europe+2016-10-11+free+osm","amp;tr":["udp%3A%2F%2Ftracker.leechers-paradise.org%3A6969","udp%3A%2F%2Fzer0day.ch%3A1337","udp%3A%2F%2Fopen.demonii.com%3A1337","udp%3A%2F%2Ftracker.coppersurfer.tk%3A6969","udp%3A%2F%2Fexodus.desync.com%3A6969"],"infoHash":"37a04f3357d9662cb02e80410ea31424525e1550","infoHashBuffer":{"type":"Buffer","data":[55,160,79,51,87,217,102,44,176,46,128,65,14,163,20,36,82,94,21,80]},"announce":[],"urlList":[]}}