{"title":"AmateurCFNM 16 08 30 Adele Aspen Burglar Milked XXX MP4","uid":15828287,"size":131568811,"categoryP":"porn","categoryS":"movie_clips","magnet":"?xt=urn:btih:38fc17940691041071cf2ebb37c22377d32b936b&amp;dn=AmateurCFNM+16+08+30+Adele+Aspen+Burglar+Milked+XXX+MP4+&amp;tr=udp%3A%2F%2Ftracker.leechers-paradise.org%3A6969&amp;tr=udp%3A%2F%2Fzer0day.ch%3A1337&amp;tr=udp%3A%2F%2Fopen.demonii.com%3A1337&amp;tr=udp%3A%2F%2Ftracker.coppersurfer.tk%3A6969&amp;tr=udp%3A%2F%2Fexodus.desync.com%3A6969","seeders":0,"leechers":4,"uploader":"thfatboys","files":1,"time":1473884419,"description":"Screens: \nhttp://imgpeak.com/img-57d971325fbbd.html","torrent":{"xt":"urn:btih:38fc17940691041071cf2ebb37c22377d32b936b","amp;dn":"AmateurCFNM+16+08+30+Adele+Aspen+Burglar+Milked+XXX+MP4+","amp;tr":["udp%3A%2F%2Ftracker.leechers-paradise.org%3A6969","udp%3A%2F%2Fzer0day.ch%3A1337","udp%3A%2F%2Fopen.demonii.com%3A1337","udp%3A%2F%2Ftracker.coppersurfer.tk%3A6969","udp%3A%2F%2Fexodus.desync.com%3A6969"],"infoHash":"38fc17940691041071cf2ebb37c22377d32b936b","infoHashBuffer":{"type":"Buffer","data":[56,252,23,148,6,145,4,16,113,207,46,187,55,194,35,119,211,43,147,107]},"announce":[],"urlList":[]}}