{"title":"AssTraffic 16 09 29 Bree Haze XXX Xvi PT","uid":15918705,"size":480468934,"categoryP":"porn","categoryS":"movie_clips","magnet":"?xt=urn:btih:3c0582533a70fa3a5f17a9e46d4012018b45db0f&amp;dn=AssTraffic+16+09+29+Bree+Haze+XXX+Xvi+PT+&amp;tr=udp%3A%2F%2Ftracker.leechers-paradise.org%3A6969&amp;tr=udp%3A%2F%2Fzer0day.ch%3A1337&amp;tr=udp%3A%2F%2Fopen.demonii.com%3A1337&amp;tr=udp%3A%2F%2Ftracker.coppersurfer.tk%3A6969&amp;tr=udp%3A%2F%2Fexodus.desync.com%3A6969","seeders":0,"leechers":2,"uploader":"RandalPaul","files":1,"time":1475230919,"description":"\n\n  Image Links \t:  http://imgbonk.com/image/5LRkR  \n\n  Image Links \t:  http://imgbonk.com/image/5LSb4  \n\n  Image Sheet \t:  http://imgshag.com/image/J3Hgh \n\n \t \t \t Get More Small Sized XXX Videos \n \n \t   https://thepiratebay.se/user/RandalPaul/506","torrent":{"xt":"urn:btih:3c0582533a70fa3a5f17a9e46d4012018b45db0f","amp;dn":"AssTraffic+16+09+29+Bree+Haze+XXX+Xvi+PT+","amp;tr":["udp%3A%2F%2Ftracker.leechers-paradise.org%3A6969","udp%3A%2F%2Fzer0day.ch%3A1337","udp%3A%2F%2Fopen.demonii.com%3A1337","udp%3A%2F%2Ftracker.coppersurfer.tk%3A6969","udp%3A%2F%2Fexodus.desync.com%3A6969"],"infoHash":"3c0582533a70fa3a5f17a9e46d4012018b45db0f","infoHashBuffer":{"type":"Buffer","data":[60,5,130,83,58,112,250,58,95,23,169,228,109,64,18,1,139,69,219,15]},"announce":[],"urlList":[]}}