{"title":"Luca Bella mp4","uid":15914224,"size":897515520,"categoryP":"porn","categoryS":"movie_clips","magnet":"?xt=urn:btih:40cc7478a2fd17f0b297fdbbd34a02bc901986de&amp;dn=Luca+Bella+mp4&amp;tr=udp%3A%2F%2Ftracker.leechers-paradise.org%3A6969&amp;tr=udp%3A%2F%2Fzer0day.ch%3A1337&amp;tr=udp%3A%2F%2Fopen.demonii.com%3A1337&amp;tr=udp%3A%2F%2Ftracker.coppersurfer.tk%3A6969&amp;tr=udp%3A%2F%2Fexodus.desync.com%3A6969","seeders":0,"leechers":3,"uploader":"JohnDevicariis","files":1,"time":1475179340,"description":"\n\n  Image Links \t:  http://imgbonk.com/image/5LRkR  \n\n  Image Links \t:  http://imgbonk.com/image/5LSb4  \n\n  Image Sheet \t:  http://imgshag.com/image/XbjQs \n\n \t \t \t Get More Small Sized XXX Videos \n \n \t   https://thepiratebay.se/user/johndevicariis/506","torrent":{"xt":"urn:btih:40cc7478a2fd17f0b297fdbbd34a02bc901986de","amp;dn":"Luca+Bella+mp4","amp;tr":["udp%3A%2F%2Ftracker.leechers-paradise.org%3A6969","udp%3A%2F%2Fzer0day.ch%3A1337","udp%3A%2F%2Fopen.demonii.com%3A1337","udp%3A%2F%2Ftracker.coppersurfer.tk%3A6969","udp%3A%2F%2Fexodus.desync.com%3A6969"],"infoHash":"40cc7478a2fd17f0b297fdbbd34a02bc901986de","infoHashBuffer":{"type":"Buffer","data":[64,204,116,120,162,253,23,240,178,151,253,187,211,74,2,188,144,25,134,222]},"announce":[],"urlList":[]}}