{"title":"X-ART.Kat.Back.In.Black 1920x1080 Full HD","uid":6921067,"size":458997829,"categoryP":"porn","categoryS":"hd___movies","magnet":"?xt=urn:btih:52d52ff2611d5d9981a950e29fa7f087b2c90538&amp;dn=X-ART.Kat.Back.In.Black+1920x1080+Full+HD&amp;tr=udp%3A%2F%2Ftracker.openbittorrent.com%3A80&amp;tr=udp%3A%2F%2Fopen.demonii.com%3A1337&amp;tr=udp%3A%2F%2Ftracker.coppersurfer.tk%3A6969&amp;tr=udp%3A%2F%2Fexodus.desync.com%3A6969","seeders":0,"leechers":1,"uploader":"vormisseed","files":1,"time":1325223158,"description":" &lt;a href=&quot;http://imagekiz.com/db29j/kat.back.in.black.html&quot; rel=&quot;nofollow&quot; target=&quot;_NEW&quot;&gt;http://imagekiz.com/db29j/kat.back.in.black.html&lt;/a&gt;","torrent":{"xt":"urn:btih:52d52ff2611d5d9981a950e29fa7f087b2c90538","amp;dn":"X-ART.Kat.Back.In.Black+1920x1080+Full+HD","amp;tr":["udp%3A%2F%2Ftracker.openbittorrent.com%3A80","udp%3A%2F%2Fopen.demonii.com%3A1337","udp%3A%2F%2Ftracker.coppersurfer.tk%3A6969","udp%3A%2F%2Fexodus.desync.com%3A6969"],"infoHash":"52d52ff2611d5d9981a950e29fa7f087b2c90538","infoHashBuffer":{"type":"Buffer","data":[82,213,47,242,97,29,93,153,129,169,80,226,159,167,240,135,178,201,5,56]},"announce":[],"urlList":[]}}