{"title":"EvilAngel - Abbie Cat (Roccos Abbondanza 5) NEW 01 October 2016","uid":15928314,"size":382497996,"categoryP":"porn","categoryS":"movie_clips","magnet":"?xt=urn:btih:5e79ca8a4550a877a5f81f2ae1571ba43eb4b36e&amp;dn=EvilAngel+-+Abbie+Cat+%28Roccos+Abbondanza+5%29+NEW+01+October+2016&amp;tr=udp%3A%2F%2Ftracker.leechers-paradise.org%3A6969&amp;tr=udp%3A%2F%2Fzer0day.ch%3A1337&amp;tr=udp%3A%2F%2Fopen.demonii.com%3A1337&amp;tr=udp%3A%2F%2Ftracker.coppersurfer.tk%3A6969&amp;tr=udp%3A%2F%2Fexodus.desync.com%3A6969","seeders":0,"leechers":3,"uploader":"xxxlavalxxx","files":2,"time":1475331589,"description":"After her car breaks down in the country, dark-haired, busty Euro-bitch Abbie Cat gets rescued by handsome motorcyclist Kid Jamaica. Back at his garage, Abbie becomes frustrated when he doesn't respond to her seductive hints -- so she pushes him onto his back and dominates Jamaica with her pretty bare feet. Soon the sultry slut is getting her pussy and asshole pounded by his huge black cock. Following an intense anal reaming, Abbie enjoys a taste of creamy jizz.\r\nCategories\r\nInterracial, Hardcore, Big Tits, Anal, Deepthroat, Titty Fuck, Foot, Blowjob, Big Dick, College\r\n \nhttp://imgdone.com/viewer.php?file=44520008596834577833.jpg\r\n \nhttp://imgdone.com/viewer.php?file=75615386021676835258.jpg","torrent":{"xt":"urn:btih:5e79ca8a4550a877a5f81f2ae1571ba43eb4b36e","amp;dn":"EvilAngel+-+Abbie+Cat+%28Roccos+Abbondanza+5%29+NEW+01+October+2016","amp;tr":["udp%3A%2F%2Ftracker.leechers-paradise.org%3A6969","udp%3A%2F%2Fzer0day.ch%3A1337","udp%3A%2F%2Fopen.demonii.com%3A1337","udp%3A%2F%2Ftracker.coppersurfer.tk%3A6969","udp%3A%2F%2Fexodus.desync.com%3A6969"],"infoHash":"5e79ca8a4550a877a5f81f2ae1571ba43eb4b36e","infoHashBuffer":{"type":"Buffer","data":[94,121,202,138,69,80,168,119,165,248,31,42,225,87,27,164,62,180,179,110]},"announce":[],"urlList":[]}}