{"title":"Castle S02E23 (DVDRip) - NL Subs - StRaLa","uid":6924014,"size":366950742,"categoryP":"video","categoryS":"tv_shows","magnet":"?xt=urn:btih:605f8c1cf0bafba00a7b3e14154b06868e42ee8b&amp;dn=Castle+S02E23+%28DVDRip%29+-+NL+Subs+-+StRaLa&amp;tr=udp%3A%2F%2Ftracker.openbittorrent.com%3A80&amp;tr=udp%3A%2F%2Fopen.demonii.com%3A1337&amp;tr=udp%3A%2F%2Ftracker.coppersurfer.tk%3A6969&amp;tr=udp%3A%2F%2Fexodus.desync.com%3A6969","seeders":0,"leechers":1,"uploader":"St-Ra-La","files":-1,"time":1325383580,"description":"Castle S02E23 (DVDrip)\n\nIMDB: &lt;a href=&quot; http://www.imdb.com/title/tt1219024/&quot; rel=&quot;nofollow&quot; target=&quot;_NEW&quot;&gt; http://www.imdb.com/title/tt1219024/&lt;/a&gt;\n\nCategorie: TV Serie\n\nFormat : AVI (XVID)\nVideo: MPEG-4 Visual\nAspect: 624 x 352\n\nAudio: English, MPEG Audio (MP3)\nInfos: 2 (ch) kanalen, 48,0 KHz\n\nDutch ( NL ) Hardcoded Subs!\n\nAlle eer aan de originele vertalers, ik heb alleen voor de liefhebbers de subs ingebakken.\n\nStRaLa \t","torrent":{"xt":"urn:btih:605f8c1cf0bafba00a7b3e14154b06868e42ee8b","amp;dn":"Castle+S02E23+%28DVDRip%29+-+NL+Subs+-+StRaLa","amp;tr":["udp%3A%2F%2Ftracker.openbittorrent.com%3A80","udp%3A%2F%2Fopen.demonii.com%3A1337","udp%3A%2F%2Ftracker.coppersurfer.tk%3A6969","udp%3A%2F%2Fexodus.desync.com%3A6969"],"infoHash":"605f8c1cf0bafba00a7b3e14154b06868e42ee8b","infoHashBuffer":{"type":"Buffer","data":[96,95,140,28,240,186,251,160,10,123,62,20,21,75,6,134,142,66,238,139]},"announce":[],"urlList":[]}}