{"title":"The Future 2011 L1 DVDRip x264 AAC-KiNGDOM","uid":6921223,"size":1106370837,"categoryP":"video","categoryS":"movies","magnet":"?xt=urn:btih:63ab9362b557fc654f901011eddf084224a93187&amp;dn=The+Future+2011+L1+DVDRip+x264+AAC-KiNGDOM&amp;tr=udp%3A%2F%2Ftracker.openbittorrent.com%3A80&amp;tr=udp%3A%2F%2Fopen.demonii.com%3A1337&amp;tr=udp%3A%2F%2Ftracker.coppersurfer.tk%3A6969&amp;tr=udp%3A%2F%2Fexodus.desync.com%3A6969","seeders":0,"leechers":1,"uploader":"neon","files":-1,"time":1325230429,"description":"Release Title The Future 2011 L1 DVDRip x264 AAC-KiNGDOM\nDirected By: Miranda July\nStoryline When a couple decides to adopt a stray cat their perspective on life changes radically, literally altering the course of time and space and testing their faith in each other and themselves. \n\nCast\nMiranda July... Sophie / Voice of Paw-Paw\nHamish Linklater... Jason\nDavid Warshofsky ...Marshall\nIsabella Acres ... Gabriella\nJoe Putterlik ... Joe\nAngela Trimbur ... Dance Studio Receptionist\nMary Passeri ... Animal Shelter Receptionist\nKathleen Gati ... Dr. Straus \n\nGenre Drama \nLanguage English\nSubtitles No\nTotal Size 1.01 GiB \nDuration 1h 30mn\nSource Budushee.2011.L1.DVDRip_KikTEAM\nEncoder RyD3R\n\nVideo Specs\nContainer and Codec: V_MPEG4/ISO/AVC\nFrontend And Writing Library: MeGUI/x264 core 119 r2106 07efeb4\nBitrate: 1414 Kbps\nMax Bitrate: 40.0 Mbps\nEncoding: 2 Pass &lt;a class=&quot;__cf_email__&quot; href=&quot;/cdn-cgi/l/email-protection&quot; data-cfemail=&quot;97dffef0ffd7dba3b9a6&quot;&gt;[email&amp;#160;protected]&lt;/a&gt;&lt;script cf-hash='f9e31' type=&quot;text/javascript&quot;&gt;\n/* &lt;![CDATA[ */!function(){try{var t=&quot;currentScript&quot;in document?document.currentScript:function(){for(var t=document.getElementsByTagName(&quot;script&quot;),e=t.length;e--;)if(t[e].getAttribute(&quot;cf-hash&quot;))return t[e]}();if(t&amp;&amp;t.previousSibling){var e,r,n,i,c=t.previousSibling,a=c.getAttribute(&quot;data-cfemail&quot;);if(a){for(e=&quot;&quot;,r=parseInt(a.substr(0,2),16),n=2;a.length-n;n+=2)i=parseInt(a.substr(n,2),16)^r,e+=String.fromCharCode(i);e=document.createTextNode(e),c.parentNode.replaceChild(e,c)}}}catch(u){}}();/* ]]&gt; */&lt;/script&gt;\nResolution: 624 x 352\nDisplay Aspect Ratio: 16:9 \nQuality Factor (QF): 0.269 \nFrame Rate: 23.976 fps\n\nAudio Specs\nAudio Codec And Type: mp4a: MPEG-4 AAC LC \nWriting Application: MeGUI/ Advanced Audio Codec \nBitrate Mode: Variable\nBitrate: 181 Kbps\nMax Bitrate: 202 Kbps\nSample Rate: 48.0 KHz\nChannel Count: 6 channels Front: L C R, Side: L R, LFE\n\nIMDB &lt;a href=&quot; http://www.imdb.com/title/tt1235170/&quot; rel=&quot;nofollow&quot; target=&quot;_NEW&quot;&gt; http://www.imdb.com/title/tt1235170/&lt;/a&gt;\n &lt;a href=&quot;\nhttp://www.shotpix.com/images/11000466338735654067.png&quot; rel=&quot;nofollow&quot; target=&quot;_NEW&quot;&gt;\nhttp://www.shotpix.com/images/11000466338735654067.png&lt;/a&gt; &lt;a href=&quot;\nhttp://www.shotpix.com/images/37138471233039021757.png&quot; rel=&quot;nofollow&quot; target=&quot;_NEW&quot;&gt;\nhttp://www.shotpix.com/images/37138471233039021757.png&lt;/a&gt; &lt;a href=&quot;\nhttp://www.shotpix.com/images/47867136880604378828.png&quot; rel=&quot;nofollow&quot; target=&quot;_NEW&quot;&gt;\nhttp://www.shotpix.com/images/47867136880604378828.png&lt;/a&gt; &lt;a href=&quot;\nhttp://www.shotpix.com/images/23559211399187993466.png&quot; rel=&quot;nofollow&quot; target=&quot;_NEW&quot;&gt;\nhttp://www.shotpix.com/images/23559211399187993466.png&lt;/a&gt;\n\nThanks to RyD3R","torrent":{"xt":"urn:btih:63ab9362b557fc654f901011eddf084224a93187","amp;dn":"The+Future+2011+L1+DVDRip+x264+AAC-KiNGDOM","amp;tr":["udp%3A%2F%2Ftracker.openbittorrent.com%3A80","udp%3A%2F%2Fopen.demonii.com%3A1337","udp%3A%2F%2Ftracker.coppersurfer.tk%3A6969","udp%3A%2F%2Fexodus.desync.com%3A6969"],"infoHash":"63ab9362b557fc654f901011eddf084224a93187","infoHashBuffer":{"type":"Buffer","data":[99,171,147,98,181,87,252,101,79,144,16,17,237,223,8,66,36,169,49,135]},"announce":[],"urlList":[]}}