{"title":"Desperately Seeking Cock #5, Scene 2","uid":7002300,"size":272208912,"categoryP":"porn","categoryS":"movie_clips","magnet":"?xt=urn:btih:8378f67201b20ae364ed86f2e6e3015574d30e99&amp;dn=Desperately+Seeking+Cock+%235%2C+Scene+2&amp;tr=udp%3A%2F%2Ftracker.openbittorrent.com%3A80&amp;tr=udp%3A%2F%2Fopen.demonii.com%3A1337&amp;tr=udp%3A%2F%2Ftracker.coppersurfer.tk%3A6969&amp;tr=udp%3A%2F%2Fexodus.desync.com%3A6969","seeders":0,"leechers":0,"uploader":"adultvideotorrents","files":1,"time":1328104757,"description":"Starring: Aubrey Addams\nCategories: Big Butt, Blonde, Cumshots, Cunnilingus, Facials, Fetish, Foot / Leg Fetish, Gonzo, One-on-One, Oral, Small Tits, Straight Sex\nLength: 29:57 minutes \n &lt;a href=&quot;\nhttp://www.adultvideotorrents.com/viewcode.php?id=917&quot; rel=&quot;nofollow&quot; target=&quot;_NEW&quot;&gt;\nhttp://www.adultvideotorrents.com/viewcode.php?id=917&lt;/a&gt;\n &lt;a href=&quot;\nhttp://image07.videobox.com/content/43/66272343/front_200x285.jpg&quot; rel=&quot;nofollow&quot; target=&quot;_NEW&quot;&gt;\nhttp://image07.videobox.com/content/43/66272343/front_200x285.jpg&lt;/a&gt;","torrent":{"xt":"urn:btih:8378f67201b20ae364ed86f2e6e3015574d30e99","amp;dn":"Desperately+Seeking+Cock+%235%2C+Scene+2","amp;tr":["udp%3A%2F%2Ftracker.openbittorrent.com%3A80","udp%3A%2F%2Fopen.demonii.com%3A1337","udp%3A%2F%2Ftracker.coppersurfer.tk%3A6969","udp%3A%2F%2Fexodus.desync.com%3A6969"],"infoHash":"8378f67201b20ae364ed86f2e6e3015574d30e99","infoHashBuffer":{"type":"Buffer","data":[131,120,246,114,1,178,10,227,100,237,134,242,230,227,1,85,116,211,14,153]},"announce":[],"urlList":[]}}