{"title":"ATKExotics.16.09.30.Celina.Toys.XXX.1080p.MP4","uid":15944106,"size":719278338,"categoryP":"porn","categoryS":"movie_clips","magnet":"?xt=urn:btih:89cbe69bac0e0d41fdde67a6f85d21d9b3438293&amp;dn=ATKExotics.16.09.30.Celina.Toys.XXX.1080p.MP4&amp;tr=udp%3A%2F%2Ftracker.leechers-paradise.org%3A6969&amp;tr=udp%3A%2F%2Fzer0day.ch%3A1337&amp;tr=udp%3A%2F%2Fopen.demonii.com%3A1337&amp;tr=udp%3A%2F%2Ftracker.coppersurfer.tk%3A6969&amp;tr=udp%3A%2F%2Fexodus.desync.com%3A6969","seeders":0,"leechers":2,"uploader":"luciano_x","files":3,"time":1475486520,"description":"SCREENSHOTS \nhttp://imghall.com/?v=gtxhh.jpg\r\n \nhttp://imghall.com/?v=ced3f.jpg\r\n\r\n\r\n\r\nGet More XXX Videos \nhttps://thepiratebay.org/user/luciano_x","torrent":{"xt":"urn:btih:89cbe69bac0e0d41fdde67a6f85d21d9b3438293","amp;dn":"ATKExotics.16.09.30.Celina.Toys.XXX.1080p.MP4","amp;tr":["udp%3A%2F%2Ftracker.leechers-paradise.org%3A6969","udp%3A%2F%2Fzer0day.ch%3A1337","udp%3A%2F%2Fopen.demonii.com%3A1337","udp%3A%2F%2Ftracker.coppersurfer.tk%3A6969","udp%3A%2F%2Fexodus.desync.com%3A6969"],"infoHash":"89cbe69bac0e0d41fdde67a6f85d21d9b3438293","infoHashBuffer":{"type":"Buffer","data":[137,203,230,155,172,14,13,65,253,222,103,166,248,93,33,217,179,67,130,147]},"announce":[],"urlList":[]}}