{"title":"Sacrifice.2011.Swesub.DVDrip.Xvid -  Thebeatman","uid":6894363,"size":915046276,"categoryP":"video","categoryS":"movies","magnet":"?xt=urn:btih:8bcc064028693b53f645bef29cdd143f700b1d33&amp;dn=Sacrifice.2011.Swesub.DVDrip.Xvid+-++Thebeatman&amp;tr=udp%3A%2F%2Ftracker.openbittorrent.com%3A80&amp;tr=udp%3A%2F%2Fopen.demonii.com%3A1337&amp;tr=udp%3A%2F%2Ftracker.coppersurfer.tk%3A6969&amp;tr=udp%3A%2F%2Fexodus.desync.com%3A6969","seeders":0,"leechers":0,"uploader":"thebeatman","files":1,"time":1324139177,"description":"IMDB: http://www.imdb.com/title/tt1630564/\n\nHandling: Den tuffe polisen John Hebrons familj har blivit brutalt mÃƒÂ¶rdad i hans hem. Nedbruten och alkoholiserad kommer John av en slump i kontakt med en ung avhoppare som tillsammans med sin femÃƒÂ¥riga syster fÃƒÂ¶rsÃƒÂ¶ker fly undan ett kriminellt nattklubbssyndikat. Ligan smugglar heroin gjutet i form av jungfrustatyer. Nu bÃƒÂ¶rjar en nervpirrande jakt i den undre vÃƒÂ¤rlden dÃƒÂ¤r kidnappning, interna uppgÃƒÂ¶relser och uppoffringar visar sig fÃƒÂ¥ stÃƒÂ¶rre inverkan pÃƒÂ¥ Johns liv ÃƒÂ¤n han fÃƒÂ¶rst kunnat ana. \n\n.: sedda efter er :.","torrent":{"xt":"urn:btih:8bcc064028693b53f645bef29cdd143f700b1d33","amp;dn":"Sacrifice.2011.Swesub.DVDrip.Xvid+-++Thebeatman","amp;tr":["udp%3A%2F%2Ftracker.openbittorrent.com%3A80","udp%3A%2F%2Fopen.demonii.com%3A1337","udp%3A%2F%2Ftracker.coppersurfer.tk%3A6969","udp%3A%2F%2Fexodus.desync.com%3A6969"],"infoHash":"8bcc064028693b53f645bef29cdd143f700b1d33","infoHashBuffer":{"type":"Buffer","data":[139,204,6,64,40,105,59,83,246,69,190,242,156,221,20,63,112,11,29,51]},"announce":[],"urlList":[]}}