{"title":"Restless 2011 BRRip AC3 XViD-RemixHD","uid":6896291,"size":1495480333,"categoryP":"video","categoryS":"movies","magnet":"?xt=urn:btih:a53290d2d1b27bff15ff157b1ca03585654ae8c3&amp;dn=Restless+2011+BRRip+AC3+XViD-RemixHD&amp;tr=udp%3A%2F%2Ftracker.openbittorrent.com%3A80&amp;tr=udp%3A%2F%2Fopen.demonii.com%3A1337&amp;tr=udp%3A%2F%2Ftracker.coppersurfer.tk%3A6969&amp;tr=udp%3A%2F%2Fexodus.desync.com%3A6969","seeders":0,"leechers":1,"uploader":"HeroMaster","files":-1,"time":1324218550,"description":"******************************************************************************\n                      \n                    Restless.2011.BRRip.AC3.XViD-RemixHD\n\n******************************************************************************\n\n\nGeneral Information:\n\n\nSample Included......: yes\nSource...............: 720p.x264.DTS-HDChina Thanks\nContainer............: AVI\nLength...............: 1h 31mn\nSize.................: 1.37 GiB\nTotal Bitrate........: 2 154 Kbps\nIMDb Information.....: http://www.imdb.com/title/tt1498569/\nGenre................: Drama\n\n\nAudio Info:\n\n\nCodec................: AC3\nBitrate..............: 448 Kbps  \nChannels.............: 6\nLanguage.............: English\nSubtitles............: None\n\n\nVideo Info (Tweaked and Sharpened):\n\n\nCodec ID.............: XViD\nType.................: AVI\nResolution...........:720x384\nAspect Ratio.........:1.875\nQ Frame..............: 0.120\nBitrate..............: 1 696 Kbps\nFramerate............: 23.976 fps\n\n\nPoster:\n\n &lt;a href=&quot;\nhttp://i.imgur.com/0MmSU.jpg&quot; rel=&quot;nofollow&quot; target=&quot;_NEW&quot;&gt;\nhttp://i.imgur.com/0MmSU.jpg&lt;/a&gt;\n\n\nScreens:\n\n &lt;a href=&quot;\nhttp://i.imgur.com/aUXWJ.png&quot; rel=&quot;nofollow&quot; target=&quot;_NEW&quot;&gt;\nhttp://i.imgur.com/aUXWJ.png&lt;/a&gt;\n\n &lt;a href=&quot;\nhttp://i.imgur.com/fSs6O.png&quot; rel=&quot;nofollow&quot; target=&quot;_NEW&quot;&gt;\nhttp://i.imgur.com/fSs6O.png&lt;/a&gt;\n\n &lt;a href=&quot;\nhttp://i.imgur.com/s7u2z.png&quot; rel=&quot;nofollow&quot; target=&quot;_NEW&quot;&gt;\nhttp://i.imgur.com/s7u2z.png&lt;/a&gt;\n\n\nENJOY!","torrent":{"xt":"urn:btih:a53290d2d1b27bff15ff157b1ca03585654ae8c3","amp;dn":"Restless+2011+BRRip+AC3+XViD-RemixHD","amp;tr":["udp%3A%2F%2Ftracker.openbittorrent.com%3A80","udp%3A%2F%2Fopen.demonii.com%3A1337","udp%3A%2F%2Ftracker.coppersurfer.tk%3A6969","udp%3A%2F%2Fexodus.desync.com%3A6969"],"infoHash":"a53290d2d1b27bff15ff157b1ca03585654ae8c3","infoHashBuffer":{"type":"Buffer","data":[165,50,144,210,209,178,123,255,21,255,21,123,28,160,53,133,101,74,232,195]},"announce":[],"urlList":[]}}