{"title":"Marie McCray - I Have A Wife","uid":6987819,"size":146220930,"categoryP":"porn","categoryS":"movie_clips","magnet":"?xt=urn:btih:a6edcd344e7febada04b9f24ed1d6f6a7e0005b3&amp;dn=Marie+McCray+-+I+Have+A+Wife&amp;tr=udp%3A%2F%2Ftracker.openbittorrent.com%3A80&amp;tr=udp%3A%2F%2Fopen.demonii.com%3A1337&amp;tr=udp%3A%2F%2Ftracker.coppersurfer.tk%3A6969&amp;tr=udp%3A%2F%2Fexodus.desync.com%3A6969","seeders":0,"leechers":1,"uploader":"Programsmith","files":1,"time":1327623100,"description":"Screens:\n &lt;a href=&quot;\nhttp://www.pixzilla.org/show.php/2637_19.jpg.html&quot; rel=&quot;nofollow&quot; target=&quot;_NEW&quot;&gt;\nhttp://www.pixzilla.org/show.php/2637_19.jpg.html&lt;/a&gt;\n &lt;a href=&quot;\nhttp://www.pixzilla.org/show.php/2636_019.jpg.html&quot; rel=&quot;nofollow&quot; target=&quot;_NEW&quot;&gt;\nhttp://www.pixzilla.org/show.php/2636_019.jpg.html&lt;/a&gt;","torrent":{"xt":"urn:btih:a6edcd344e7febada04b9f24ed1d6f6a7e0005b3","amp;dn":"Marie+McCray+-+I+Have+A+Wife","amp;tr":["udp%3A%2F%2Ftracker.openbittorrent.com%3A80","udp%3A%2F%2Fopen.demonii.com%3A1337","udp%3A%2F%2Ftracker.coppersurfer.tk%3A6969","udp%3A%2F%2Fexodus.desync.com%3A6969"],"infoHash":"a6edcd344e7febada04b9f24ed1d6f6a7e0005b3","infoHashBuffer":{"type":"Buffer","data":[166,237,205,52,78,127,235,173,160,75,159,36,237,29,111,106,126,0,5,179]},"announce":[],"urlList":[]}}