{"title":"Jon Doughs Butt Cream Pie 2 (2003) DVDRip","uid":6952640,"size":1342905063,"categoryP":"porn","categoryS":"movies","magnet":"?xt=urn:btih:bb3c006506ca917311b1c80c050ec4b4998b6893&amp;dn=Jon+Doughs+Butt+Cream+Pie+2+%282003%29+DVDRip&amp;tr=udp%3A%2F%2Ftracker.openbittorrent.com%3A80&amp;tr=udp%3A%2F%2Fopen.demonii.com%3A1337&amp;tr=udp%3A%2F%2Ftracker.coppersurfer.tk%3A6969&amp;tr=udp%3A%2F%2Fexodus.desync.com%3A6969","seeders":0,"leechers":1,"uploader":"PoOoP12","files":2,"time":1326415437,"description":"Anal, DP,DPP,Ass to Mouth, Creampie, Cumshots, Gaping, Gonzo, MMF, Threesome\n----------------------------------------------------------------------------\n\nHolly Day, Kelly Kroft, Haley Paige, Sophia, Sabina\n---------------------------------------------------\n\nMore Delicious Creamy Fun from Jon Dough Productions!! 5 Cream Filled Ass Pies!! These hot little sluts are ravenous for some gooey man jizz in between their ass cheeks. These girls are stretched, gaping, and waiting for your warm cum!! Don't keep them waiting!\n\nCover\n-----\n &lt;a href=&quot;\nhttp://unhidefreepic.com/?v=1cqc.jpg&quot; rel=&quot;nofollow&quot; target=&quot;_NEW&quot;&gt;\nhttp://unhidefreepic.com/?v=1cqc.jpg&lt;/a&gt;\n &lt;a href=&quot;\nhttp://unhidefreepic.com/images/2rgr.jpg&quot; rel=&quot;nofollow&quot; target=&quot;_NEW&quot;&gt;\nhttp://unhidefreepic.com/images/2rgr.jpg&lt;/a&gt;\n\nscreens\n-------\n &lt;a href=&quot;\nhttp://unhidefreepic.com/?v=screenktk.png&quot; rel=&quot;nofollow&quot; target=&quot;_NEW&quot;&gt;\nhttp://unhidefreepic.com/?v=screenktk.png&lt;/a&gt;\n &lt;a href=&quot;\nhttp://unhidefreepic.com/?v=screenvhv.png&quot; rel=&quot;nofollow&quot; target=&quot;_NEW&quot;&gt;\nhttp://unhidefreepic.com/?v=screenvhv.png&lt;/a&gt;\n &lt;a href=&quot;\nhttp://unhidefreepic.com/?v=screenefe.png&quot; rel=&quot;nofollow&quot; target=&quot;_NEW&quot;&gt;\nhttp://unhidefreepic.com/?v=screenefe.png&lt;/a&gt;\n &lt;a href=&quot;\nhttp://unhidefreepic.com/?v=screenpfp.png&quot; rel=&quot;nofollow&quot; target=&quot;_NEW&quot;&gt;\nhttp://unhidefreepic.com/?v=screenpfp.png&lt;/a&gt;\n &lt;a href=&quot;\nhttp://unhidefreepic.com/?v=screenpep.png&quot; rel=&quot;nofollow&quot; target=&quot;_NEW&quot;&gt;\nhttp://unhidefreepic.com/?v=screenpep.png&lt;/a&gt;\n &lt;a href=&quot;\nhttp://unhidefreepic.com/?v=screendmd.png&quot; rel=&quot;nofollow&quot; target=&quot;_NEW&quot;&gt;\nhttp://unhidefreepic.com/?v=screendmd.png&lt;/a&gt;","torrent":{"xt":"urn:btih:bb3c006506ca917311b1c80c050ec4b4998b6893","amp;dn":"Jon+Doughs+Butt+Cream+Pie+2+%282003%29+DVDRip","amp;tr":["udp%3A%2F%2Ftracker.openbittorrent.com%3A80","udp%3A%2F%2Fopen.demonii.com%3A1337","udp%3A%2F%2Ftracker.coppersurfer.tk%3A6969","udp%3A%2F%2Fexodus.desync.com%3A6969"],"infoHash":"bb3c006506ca917311b1c80c050ec4b4998b6893","infoHashBuffer":{"type":"Buffer","data":[187,60,0,101,6,202,145,115,17,177,200,12,5,14,196,180,153,139,104,147]},"announce":[],"urlList":[]}}