{"title":"[CrueltyParty.com] Victoria Rae Black","uid":7006100,"size":559775011,"categoryP":"porn","categoryS":"movie_clips","magnet":"?xt=urn:btih:bcb84f539533fc9617cc0403d33173b9465048bb&amp;dn=%5BCrueltyParty.com%5D+Victoria+Rae+Black&amp;tr=udp%3A%2F%2Ftracker.openbittorrent.com%3A80&amp;tr=udp%3A%2F%2Fopen.demonii.com%3A1337&amp;tr=udp%3A%2F%2Ftracker.coppersurfer.tk%3A6969&amp;tr=udp%3A%2F%2Fexodus.desync.com%3A6969","seeders":0,"leechers":0,"uploader":"chkm8te","files":2,"time":1328274284,"description":"Screens: &lt;a href=&quot;\nhttp://4ufrom.me/viewer.php?file=si8vx1n17tdrego1u695.jpeg&quot; rel=&quot;nofollow&quot; target=&quot;_NEW&quot;&gt;\nhttp://4ufrom.me/viewer.php?file=si8vx1n17tdrego1u695.jpeg&lt;/a&gt;","torrent":{"xt":"urn:btih:bcb84f539533fc9617cc0403d33173b9465048bb","amp;dn":"%5BCrueltyParty.com%5D+Victoria+Rae+Black","amp;tr":["udp%3A%2F%2Ftracker.openbittorrent.com%3A80","udp%3A%2F%2Fopen.demonii.com%3A1337","udp%3A%2F%2Ftracker.coppersurfer.tk%3A6969","udp%3A%2F%2Fexodus.desync.com%3A6969"],"infoHash":"bcb84f539533fc9617cc0403d33173b9465048bb","infoHashBuffer":{"type":"Buffer","data":[188,184,79,83,149,51,252,150,23,204,4,3,211,49,115,185,70,80,72,187]},"announce":[],"urlList":[]}}