{"title":"Great.Barrier.Reef.S01E01.Natures.Miracles.HDTV.XviD-C4TV","uid":6925320,"size":575834112,"categoryP":"video","categoryS":"tv_shows","magnet":"?xt=urn:btih:be7565607e9a6850f0dd130f628856618e325710&amp;dn=Great.Barrier.Reef.S01E01.Natures.Miracles.HDTV.XviD-C4TV&amp;tr=udp%3A%2F%2Ftracker.openbittorrent.com%3A80&amp;tr=udp%3A%2F%2Fopen.demonii.com%3A1337&amp;tr=udp%3A%2F%2Ftracker.coppersurfer.tk%3A6969&amp;tr=udp%3A%2F%2Fexodus.desync.com%3A6969","seeders":0,"leechers":1,"uploader":"maximersk","files":1,"time":1325459906,"description":"Great.Barrier.Reef.S01E01.Natures.Miracles.HDTV.XviD-C4TV\n\n\n\n\n\n\n\n\n\nThis and many more current US TV series on &lt;a href=&quot;\nhttp://tv-scene.com/index.php&quot; rel=&quot;nofollow&quot; target=&quot;_NEW&quot;&gt;\nhttp://tv-scene.com/index.php&lt;/a&gt;\nAll seeded from high speed seedboxes\nMembership is free and open\n\nsorry folks, a little late with these. We are switching to all .avi files :D\nNo more rar files!!!\n\nGreat Barrier Reef S01e01 Natures Miracles Hdtv Xvid-C4tv\n===================================================\n\nTitle: Great Barrier Reef\nAired On Channel: BBC HD\nAiring Date: 10/10/2012\nSource: HDTV\nResolution: 624 x 352\nAspect Ratio: WS 1.773\nFramerate: 25 FPS\nVideo Codec: XviD\nAudio: MP3 @ 128kbps VBR 48KHz\nSize: 550 MB\nLink: http://www.tvrage.com/shows/id-30428\n\nDESCRiPTiON\nGreat Barrier Reef sees the cameras folloing Monty Halls as he finds out more\nabout Australia's Great Barrier Reef, which is one of the natural wonders of\nthe world and the largest living structure on the planet\n\n\n\n\n\n\n","torrent":{"xt":"urn:btih:be7565607e9a6850f0dd130f628856618e325710","amp;dn":"Great.Barrier.Reef.S01E01.Natures.Miracles.HDTV.XviD-C4TV","amp;tr":["udp%3A%2F%2Ftracker.openbittorrent.com%3A80","udp%3A%2F%2Fopen.demonii.com%3A1337","udp%3A%2F%2Ftracker.coppersurfer.tk%3A6969","udp%3A%2F%2Fexodus.desync.com%3A6969"],"infoHash":"be7565607e9a6850f0dd130f628856618e325710","infoHashBuffer":{"type":"Buffer","data":[190,117,101,96,126,154,104,80,240,221,19,15,98,136,86,97,142,50,87,16]},"announce":[],"urlList":[]}}