{"title":"BrazzersExxtra Lela Star Extra Amenities mp4s","uid":15836715,"size":347916507,"categoryP":"porn","categoryS":"movie_clips","magnet":"?xt=urn:btih:be90b587a540fc557ee24458101d00324a55851b&amp;dn=BrazzersExxtra+Lela+Star+Extra+Amenities+mp4s&amp;tr=udp%3A%2F%2Ftracker.leechers-paradise.org%3A6969&amp;tr=udp%3A%2F%2Fzer0day.ch%3A1337&amp;tr=udp%3A%2F%2Fopen.demonii.com%3A1337&amp;tr=udp%3A%2F%2Ftracker.coppersurfer.tk%3A6969&amp;tr=udp%3A%2F%2Fexodus.desync.com%3A6969","seeders":0,"leechers":3,"uploader":"RandalPaul","files":2,"time":1473982423,"description":"\n\n  Image Links \t:    \n\n  Image Links \t:    \n\n  Image Sheet \t:   \n\n \t \t \t Get More Small Sized XXX Videos \n \n \t   https://thepiratebay.se/user/RandalPaul/","torrent":{"xt":"urn:btih:be90b587a540fc557ee24458101d00324a55851b","amp;dn":"BrazzersExxtra+Lela+Star+Extra+Amenities+mp4s","amp;tr":["udp%3A%2F%2Ftracker.leechers-paradise.org%3A6969","udp%3A%2F%2Fzer0day.ch%3A1337","udp%3A%2F%2Fopen.demonii.com%3A1337","udp%3A%2F%2Ftracker.coppersurfer.tk%3A6969","udp%3A%2F%2Fexodus.desync.com%3A6969"],"infoHash":"be90b587a540fc557ee24458101d00324a55851b","infoHashBuffer":{"type":"Buffer","data":[190,144,181,135,165,64,252,85,126,226,68,88,16,29,0,50,74,85,133,27]},"announce":[],"urlList":[]}}