{"title":"Filthy Cocksucking Auditions (Evil Angel Ea-Productions) DVDRip.","uid":6956451,"size":731947008,"categoryP":"porn","categoryS":"movies","magnet":"?xt=urn:btih:cb603388bbeffb3f3407772a9c650cc1b0ddd379&amp;dn=Filthy+Cocksucking+Auditions+%28Evil+Angel+Ea-Productions%29+DVDRip.&amp;tr=udp%3A%2F%2Ftracker.openbittorrent.com%3A80&amp;tr=udp%3A%2F%2Fopen.demonii.com%3A1337&amp;tr=udp%3A%2F%2Ftracker.coppersurfer.tk%3A6969&amp;tr=udp%3A%2F%2Fexodus.desync.com%3A6969","seeders":0,"leechers":0,"uploader":"scree30","files":1,"time":1326601599,"description":"Filthy Cocksucking Auditions (Evil Angel Ea-Productions) DVDRip.CD1 -01.11.2012-\n\nScreens: &lt;a href=&quot;\nhttp://www.screenerotica.com/?v=ip5LN.jpg&quot; rel=&quot;nofollow&quot; target=&quot;_NEW&quot;&gt;\nhttp://www.screenerotica.com/?v=ip5LN.jpg&lt;/a&gt;\n &lt;a href=&quot;\nhttp://www.screenerotica.com/?v=9Qnya.jpg&quot; rel=&quot;nofollow&quot; target=&quot;_NEW&quot;&gt;\nhttp://www.screenerotica.com/?v=9Qnya.jpg&lt;/a&gt;\n &lt;a href=&quot;\nhttp://www.screenerotica.com/?v=PpoWF.jpg&quot; rel=&quot;nofollow&quot; target=&quot;_NEW&quot;&gt;\nhttp://www.screenerotica.com/?v=PpoWF.jpg&lt;/a&gt;\n &lt;a href=&quot;\nhttp://www.screenerotica.com/?v=PIsm4.jpg&quot; rel=&quot;nofollow&quot; target=&quot;_NEW&quot;&gt;\nhttp://www.screenerotica.com/?v=PIsm4.jpg&lt;/a&gt;\n &lt;a href=&quot;\nhttp://www.screenerotica.com/?v=4LgJ3.jpg&quot; rel=&quot;nofollow&quot; target=&quot;_NEW&quot;&gt;\nhttp://www.screenerotica.com/?v=4LgJ3.jpg&lt;/a&gt;\n &lt;a href=&quot;\nhttp://www.screenerotica.com/?v=Kzq2J.jpg&quot; rel=&quot;nofollow&quot; target=&quot;_NEW&quot;&gt;\nhttp://www.screenerotica.com/?v=Kzq2J.jpg&lt;/a&gt;\n\nCasts:\nPhoenix Marie, Asa Akira, Dana DeArmond, Mike Adriano, Alanah Rae, Adrianna Nicole, Juelz Ventura, Chanel Preston, Jynx Maze, Alexis Silver, Jessie Andrews, Sarah Vandella, Skin Diamond, Cassandra Nix, Vicki Chase, Holly Michaels, Alexa Cruz, Tia Ling, Lyla Storm, Sasha Sweet ","torrent":{"xt":"urn:btih:cb603388bbeffb3f3407772a9c650cc1b0ddd379","amp;dn":"Filthy+Cocksucking+Auditions+%28Evil+Angel+Ea-Productions%29+DVDRip.","amp;tr":["udp%3A%2F%2Ftracker.openbittorrent.com%3A80","udp%3A%2F%2Fopen.demonii.com%3A1337","udp%3A%2F%2Ftracker.coppersurfer.tk%3A6969","udp%3A%2F%2Fexodus.desync.com%3A6969"],"infoHash":"cb603388bbeffb3f3407772a9c650cc1b0ddd379","infoHashBuffer":{"type":"Buffer","data":[203,96,51,136,187,239,251,63,52,7,119,42,156,101,12,193,176,221,211,121]},"announce":[],"urlList":[]}}