{"title":"BBC Andy Pandy 1950s60s VHS Quality Xvid.avi","uid":6907390,"size":126627840,"categoryP":"video","categoryS":"tv_shows","magnet":"?xt=urn:btih:dc06f2e5c9dda39af62bf9fbee643152a8d5f597&amp;dn=BBC+Andy+Pandy+1950s60s+VHS+Quality+Xvid.avi&amp;tr=udp%3A%2F%2Ftracker.openbittorrent.com%3A80&amp;tr=udp%3A%2F%2Fopen.demonii.com%3A1337&amp;tr=udp%3A%2F%2Ftracker.coppersurfer.tk%3A6969&amp;tr=udp%3A%2F%2Fexodus.desync.com%3A6969","seeders":0,"leechers":1,"uploader":"gasmark10","files":1,"time":1324646124,"description":"From a BBC VHS Video Tape\n\nAspect Ratio 4:3\n\nBlack n White\n\nRuntime 14 mins","torrent":{"xt":"urn:btih:dc06f2e5c9dda39af62bf9fbee643152a8d5f597","amp;dn":"BBC+Andy+Pandy+1950s60s+VHS+Quality+Xvid.avi","amp;tr":["udp%3A%2F%2Ftracker.openbittorrent.com%3A80","udp%3A%2F%2Fopen.demonii.com%3A1337","udp%3A%2F%2Ftracker.coppersurfer.tk%3A6969","udp%3A%2F%2Fexodus.desync.com%3A6969"],"infoHash":"dc06f2e5c9dda39af62bf9fbee643152a8d5f597","infoHashBuffer":{"type":"Buffer","data":[220,6,242,229,201,221,163,154,246,43,249,251,238,100,49,82,168,213,245,151]},"announce":[],"urlList":[]}}