{"title":"Gator.Boys.S01E03.Stormin.Gators.HDTV.XviD-NMBSTV","uid":6997584,"size":375891510,"categoryP":"video","categoryS":"tv_shows","magnet":"?xt=urn:btih:e52e1570b05851ba1b13289799a395c56b2b48c6&amp;dn=Gator.Boys.S01E03.Stormin.Gators.HDTV.XviD-NMBSTV&amp;tr=udp%3A%2F%2Ftracker.openbittorrent.com%3A80&amp;tr=udp%3A%2F%2Fopen.demonii.com%3A1337&amp;tr=udp%3A%2F%2Ftracker.coppersurfer.tk%3A6969&amp;tr=udp%3A%2F%2Fexodus.desync.com%3A6969","seeders":0,"leechers":1,"uploader":"TvTeam","files":5,"time":1327941210,"description":".  TD Sign UP is open until 1st of January. so you better hurry up ;) ENJOYYYYYYYYYYYYYYYYYYYYYYYYYYYYYYYYYYYYYYYYYYYY!!!!\n  &lt;a href=&quot;\nhttp://www.torrentday.com&quot; rel=&quot;nofollow&quot; target=&quot;_NEW&quot;&gt;\nhttp://www.torrentday.com&lt;/a&gt;\n\n\nTo Avoid Fakes, ALWAYS Check That The Torrent Was Added By: TvTeam.\n\n\n               www . TorrentDay . Com \n(((((((((((((= Enjoy No RAR releases =))))))))))))))))))))\n\n...................................NFO:....................................\n\n._|      _|      _|      _|      _|_|_|          _|_|_|      _|_|_|_|_|      _|      _|  \n_|_|    _|      _|_|  _|_|      _|    _|      _|                _|          _|      _|  \n_|  _|  _|      _|  _|  _|      _|_|_|          _|_|            _|          _|      _|  \n_|    _|_|      _|      _|      _|    _|            _|          _|            _|  _|    \n_|      _|      _|      _|      _|_|_|        _|_|_|            _|              _|      \n                                                                                        \n\tWe would like to thank all that has helped us along the way you know who you \nare and to the rest ............... who cares !!!!\n\n\n\nURL: --------- http://www.tvrage.com/shows/id-30517\nRel name: ---- Gator.Boys.S01E03.Stormin.Gators.HDTV.XviD-NMBSTV\nPre Date: ---- Jan/30/2012\nShow Title: -- Gator Boys\nRuntime: ----- 60\nAirtime: ----- Sunday at 09:00 pm\nNetwork: ----- Animal Planet\nCountry: ----- USA\nSource: ------ HDTV\nGenre: ------- Reality\nResolution: -- 624x352\nRelease Date: Jan/30/2012\nWe are looking for a few EU sites if you have one and would like our company email us at &lt;a class=&quot;__cf_email__&quot; href=&quot;/cdn-cgi/l/email-protection&quot; data-cfemail=&quot;8ee0e3ecfdfaf8cee6fbfde6e3efe7e2a0ede1e3&quot;&gt;[email&amp;#160;protected]&lt;/a&gt;&lt;script cf-hash='f9e31' type=&quot;text/javascript&quot;&gt;\n/* &lt;![CDATA[ */!function(){try{var t=&quot;currentScript&quot;in document?document.currentScript:function(){for(var t=document.getElementsByTagName(&quot;script&quot;),e=t.length;e--;)if(t[e].getAttribute(&quot;cf-hash&quot;))return t[e]}();if(t&amp;&amp;t.previousSibling){var e,r,n,i,c=t.previousSibling,a=c.getAttribute(&quot;data-cfemail&quot;);if(a){for(e=&quot;&quot;,r=parseInt(a.substr(0,2),16),n=2;a.length-n;n+=2)i=parseInt(a.substr(n,2),16)^r,e+=String.fromCharCode(i);e=document.createTextNode(e),c.parentNode.replaceChild(e,c)}}}catch(u){}}();/* ]]&gt; */&lt;/script&gt;","torrent":{"xt":"urn:btih:e52e1570b05851ba1b13289799a395c56b2b48c6","amp;dn":"Gator.Boys.S01E03.Stormin.Gators.HDTV.XviD-NMBSTV","amp;tr":["udp%3A%2F%2Ftracker.openbittorrent.com%3A80","udp%3A%2F%2Fopen.demonii.com%3A1337","udp%3A%2F%2Ftracker.coppersurfer.tk%3A6969","udp%3A%2F%2Fexodus.desync.com%3A6969"],"infoHash":"e52e1570b05851ba1b13289799a395c56b2b48c6","infoHashBuffer":{"type":"Buffer","data":[229,46,21,112,176,88,81,186,27,19,40,151,153,163,149,197,107,43,72,198]},"announce":[],"urlList":[]}}