{"title":"AVIATION MAGAZINES - SEPTEMBER 2016^V","uid":15914605,"size":1773167265,"categoryP":"other","categoryS":"e_books","magnet":"?xt=urn:btih:efe9753a808ce0c3e4f34d78539b1250bb33585e&amp;dn=AVIATION+MAGAZINES+-+SEPTEMBER+2016%5EV&amp;tr=udp%3A%2F%2Ftracker.leechers-paradise.org%3A6969&amp;tr=udp%3A%2F%2Fzer0day.ch%3A1337&amp;tr=udp%3A%2F%2Fopen.demonii.com%3A1337&amp;tr=udp%3A%2F%2Ftracker.coppersurfer.tk%3A6969&amp;tr=udp%3A%2F%2Fexodus.desync.com%3A6969","seeders":0,"leechers":3,"uploader":"VP52","files":41,"time":1475188189,"description":"41 magazines|PDF|Multilanguage|1,65 MB|","torrent":{"xt":"urn:btih:efe9753a808ce0c3e4f34d78539b1250bb33585e","amp;dn":"AVIATION+MAGAZINES+-+SEPTEMBER+2016%5EV","amp;tr":["udp%3A%2F%2Ftracker.leechers-paradise.org%3A6969","udp%3A%2F%2Fzer0day.ch%3A1337","udp%3A%2F%2Fopen.demonii.com%3A1337","udp%3A%2F%2Ftracker.coppersurfer.tk%3A6969","udp%3A%2F%2Fexodus.desync.com%3A6969"],"infoHash":"efe9753a808ce0c3e4f34d78539b1250bb33585e","infoHashBuffer":{"type":"Buffer","data":[239,233,117,58,128,140,224,195,228,243,77,120,83,155,18,80,187,51,88,94]},"announce":[],"urlList":[]}}