{"title":"Adorable brunette fucked on balkony.wmv","uid":6890146,"size":73664647,"categoryP":"porn","categoryS":"movie_clips","magnet":"?xt=urn:btih:f4b232edcf4a41b8a1b5bd307780ef4e3faf168d&amp;dn=Adorable+brunette+fucked+on+balkony.wmv&amp;tr=udp%3A%2F%2Ftracker.openbittorrent.com%3A80&amp;tr=udp%3A%2F%2Fopen.demonii.com%3A1337&amp;tr=udp%3A%2F%2Ftracker.coppersurfer.tk%3A6969&amp;tr=udp%3A%2F%2Fexodus.desync.com%3A6969","seeders":0,"leechers":1,"uploader":"dodgerblue","files":1,"time":1323981591,"description":" &lt;a href=&quot;http://www.shotpix.com/images/48712259600262248617.png&quot; rel=&quot;nofollow&quot; target=&quot;_NEW&quot;&gt;http://www.shotpix.com/images/48712259600262248617.png&lt;/a&gt; &lt;a href=&quot;\nhttp://www.shotpix.com/images/15827231533591899342.png&quot; rel=&quot;nofollow&quot; target=&quot;_NEW&quot;&gt;\nhttp://www.shotpix.com/images/15827231533591899342.png&lt;/a&gt;","torrent":{"xt":"urn:btih:f4b232edcf4a41b8a1b5bd307780ef4e3faf168d","amp;dn":"Adorable+brunette+fucked+on+balkony.wmv","amp;tr":["udp%3A%2F%2Ftracker.openbittorrent.com%3A80","udp%3A%2F%2Fopen.demonii.com%3A1337","udp%3A%2F%2Ftracker.coppersurfer.tk%3A6969","udp%3A%2F%2Fexodus.desync.com%3A6969"],"infoHash":"f4b232edcf4a41b8a1b5bd307780ef4e3faf168d","infoHashBuffer":{"type":"Buffer","data":[244,178,50,237,207,74,65,184,161,181,189,48,119,128,239,78,63,175,22,141]},"announce":[],"urlList":[]}}