{"title":"Environmental Science for Students Series","uid":6921684,"size":312314214,"categoryP":"video","categoryS":"other","magnet":"?xt=urn:btih:f5d029907ad0b68227fea86ac7e18e8aca705f0c&amp;dn=Environmental+Science+for+Students+Series&amp;tr=udp%3A%2F%2Ftracker.openbittorrent.com%3A80&amp;tr=udp%3A%2F%2Fopen.demonii.com%3A1337&amp;tr=udp%3A%2F%2Ftracker.coppersurfer.tk%3A6969&amp;tr=udp%3A%2F%2Fexodus.desync.com%3A6969","seeders":0,"leechers":1,"uploader":"mdusanjay","files":8,"time":1325296672,"description":"Environmental Science for Students Series\n\nEnvironmental Science for Students provides a fascinating look at Earth's environment and some of the most important environmental issues of our time. From the quality of the air that we breathe and water that we drink to the lasting effects of our reliance upon fossil fuels to power our lives, everyone is affected by environmental change. Accurate explanations, global examples and balanced viewpoints guide students in an exploration of topics that range from global climate change to the degradation of soil. Environmental experts speak about topics of interest, and noteworthy case studies showcase real-world examples. \n\nMore info on their site: &lt;a href=&quot;\nhttp://www.libraryvideo.com/product.asp?sku=V6870&quot; rel=&quot;nofollow&quot; target=&quot;_NEW&quot;&gt;\nhttp://www.libraryvideo.com/product.asp?sku=V6870&lt;/a&gt;","torrent":{"xt":"urn:btih:f5d029907ad0b68227fea86ac7e18e8aca705f0c","amp;dn":"Environmental+Science+for+Students+Series","amp;tr":["udp%3A%2F%2Ftracker.openbittorrent.com%3A80","udp%3A%2F%2Fopen.demonii.com%3A1337","udp%3A%2F%2Ftracker.coppersurfer.tk%3A6969","udp%3A%2F%2Fexodus.desync.com%3A6969"],"infoHash":"f5d029907ad0b68227fea86ac7e18e8aca705f0c","infoHashBuffer":{"type":"Buffer","data":[245,208,41,144,122,208,182,130,39,254,168,106,199,225,142,138,202,112,95,12]},"announce":[],"urlList":[]}}